{"is_userself":0,"link_protected":0,"popad":1,"file_name":"534_churentoudi.txt","file_size":"223.17 KB","file_time":"2019-12-05","file_views":2,"username":"misswuyang","email":"missw*****@163.com","reg_url":"https://www.ctfile.com/p/register","login_url":"https://www.ctfile.com/p/login","home_url":"https://home.ctfile.com","web_url":"https://www.ctfile.com","page_title":"534_churentoudi.txt - 免费高速下载","file_dir":"/dir/1210232-35428889-1585811614-69fb2e41a55f921d","userid":1210232,"file_id":412138149,"free_speed":"0 秒","software_speed":"2 秒","vip_speed":"0 秒","my_uid":0,"my_username":"","is_mb":0,"doubleclick_url":"https://doubleclick.ctfile.com/?adv&advert&mod=cpv&act=add&uid=1210232&fid=412138149&t=1585811614&k=7f5ac5cdc704f5587ef10fc05ef592ac&ref=http%3A%2F%2Fwww.aishen360.com%2Fdownload%2F%E4%B8%AA%E4%BA%BA%E4%BC%A0%E8%AE%B0.html","file_chk":"c1123ddff678be3ea6ea2f85f0873333","groups_price":{"10":570,"13":1250,"14":2430}}