{"is_userself":0,"link_protected":0,"popad":1,"file_name":"43660_说预言的恩赐.pdf","file_size":"314.38 KB","file_time":"2019-09-12","file_views":2,"username":"misswuyang","email":"missw*****@163.com","reg_url":"https://www.ctfile.com/p/register","login_url":"https://www.ctfile.com/p/login","home_url":"https://home.ctfile.com","web_url":"https://www.ctfile.com","page_title":"43660_说预言的恩赐.pdf - 免费高速下载","file_dir":"/dir/1210232-35428889-1585817310-134717b0ec32436c","userid":1210232,"file_id":397572490,"free_speed":"0 秒","software_speed":"4 秒","vip_speed":"0 秒","my_uid":0,"my_username":"","is_mb":0,"doubleclick_url":"https://doubleclick.ctfile.com/?adv&advert&mod=cpv&act=add&uid=1210232&fid=397572490&t=1585817310&k=42c5bba186ba2a7bd151faebdfdf4d1b&ref=http%3A%2F%2Fwww.aishen360.com%2Fdownload%2F%E7%81%B5%E4%BF%AE%E4%B9%A6%E7%B1%8D.html","file_chk":"bfc351a5e45873bf9e43fdbbb1b259fc","groups_price":{"10":570,"13":1250,"14":2430}}